counter.sv
module counter #(
    parameter int N = 8
) (
    input logic clk,
    input logic rst,
    input logic en,
    output logic [N-1:0] count
);
 
  always_ff @(posedge clk, posedge rst) begin
    if (rst) count <= 0;
    else if (en) count <= count + 1;
  end
 
endmodule

counter_tb.sv
`timescale 1ns / 1ps
 
module counter_tb;
 
  localparam int N = 8;  // counter bit width
  localparam int T = 10;  // clock period in ns
 
  logic clk;
  logic rst;
  logic en;
  logic [N-1:0] count;
 
  counter #(
      .N(N)
  ) uut (
      .clk(clk),
      .rst(rst),
      .en(en),
      .count(count)
  );
 
  // Clock
  always begin
    clk = 1'b1;
    #(T / 2);
    clk = 1'b0;
    #(T / 2);
  end
 
  // Async reset (over the first half cycle)
  initial begin
    rst = 1'b1;
    #(T / 2);
    rst = 1'b0;
  end
 
  // Enable on the third cycle and count for 10 cycles
  initial begin
    en = 0;
    repeat (3) @(negedge clk);
    en = 1;
    #(10 * T) $finish;
  end
 
  initial begin
    $timeformat(-9, 1, " ns", 8);
    $monitor("time=%t clk=%b rst=%b en=%b count=%2d", $time, clk, rst, en, count);
    $dumpfile("counter_tb.vcd");
    $dumpvars(0, counter_tb);
  end
 
endmodule  // counter_tb

counter_tb.vcd
$date
	Sun Nov 10 16:52:26 2024
$end
$version
	Icarus Verilog
$end
$timescale
	1ps
$end
$scope module counter_tb $end
$var wire 8 ! count [7:0] $end
$var reg 1 " clk $end
$var reg 1 # en $end
$var reg 1 $ rst $end
$scope module uut $end
$var wire 1 " clk $end
$var wire 1 # en $end
$var wire 1 $ rst $end
$var reg 8 % count [7:0] $end
$upscope $end
$upscope $end
$enddefinitions $end
#0
$dumpvars
b0 %
1$
0#
1"
b0 !
$end
#5000
0$
0"
#10000
1"
#15000
0"
#20000
1"
#25000
1#
0"
#30000
b1 !
b1 %
1"
#35000
0"
#40000
b10 !
b10 %
1"
#45000
0"
#50000
b11 !
b11 %
1"
#55000
0"
#60000
b100 !
b100 %
1"
#65000
0"
#70000
b101 !
b101 %
1"
#75000
0"
#80000
b110 !
b110 %
1"
#85000
0"
#90000
b111 !
b111 %
1"
#95000
0"
#100000
b1000 !
b1000 %
1"
#105000
0"
#110000
b1001 !
b1001 %
1"
#115000
0"
#120000
b1010 !
b1010 %
1"
